{
  "experiment_name": "shared_transformer_head_live_encoder_attention_derf_freeze_all",
  "variant": "transformer_head",
  "training_mode": "live_encoder",
  "split_meta": {
    "total_samples": 48187,
    "total_groups": 71,
    "train_samples": 37852,
    "val_samples": 4556,
    "test_samples": 5779,
    "train_groups": 55,
    "val_groups": 8,
    "test_groups": 8
  },
  "norm": "derf",
  "pooling": "attention",
  "freeze_strategy": "freeze_all",
  "epochs_ran": 29,
  "best_metric": "val_acc",
  "best_epoch": 19,
  "selected_val_acc": 0.6940298507462687,
  "selected_val_loss": 1.3614475275990836,
  "best_val_loss": 0.9886656123572426,
  "best_val_acc": 0.6940298507462687,
  "test_acc": 0.7350752725385015,
  "macro_f1": 0.7058379556632258,
  "weighted_f1": 0.731512473797562,
  "uar": 0.7049447054381376,
  "checkpoint_filename": "shared_transformer_head_live_encoder_attention_derf_freeze_all.pth",
  "history_filename": "shared_transformer_head_live_encoder_attention_derf_freeze_all_history.npz"
}